SESSION-5/ALU/alu.v
module alu(
    input [7:0] A,
    input [7:0] B,
    input [2:0] op,
    output reg [7:0] result
);

always @(*) begin
    case (op)
        3'b000: result = A + B; 
        3'b001: result = A - B; 
        3'b010: result = ~(A & B); 
        3'b011: result = A ^ B; 
	3'b100: result = ~(A | B); 
	3'b101: result = ~(A ^ B); 
		  
        default: result = 8'b00000000; 
    endcase
end

endmodule

SESSION-5/ALU/alu_tb.v
module alu_tb;

reg [7:0] A, B;
reg [2:0] op;
wire [7:0] result;

alu dut (
    .A(A),
    .B(B),
    .op(op),
    .result(result)
);
initial begin
$dumpfile("test_alu.vcd");
$dumpvars(0,alu_tb);
    A = 8'b10000000;
    B = 8'b00000001;
    op = 3'b000; 
    #10;
    op = 3'b001; 
    #10;
    op = 3'b010; 
    #10;
    op = 3'b011; 
    #10;
    op = 3'b100; 
    #10;
    op = 3'b101; 
    #10;
    op = 3'b110; 
    #10;
    op = 3'b111; 
    #10;


    #10 $finish;
end

endmodule

SESSION-5/ALU/test_alu.vcd
$date
	Wed Aug 21 13:41:32 2024
$end
$version
	Icarus Verilog
$end
$timescale
	1s
$end
$scope module alu_tb $end
$var wire 8 ! result [7:0] $end
$var reg 8 " A [7:0] $end
$var reg 8 # B [7:0] $end
$var reg 3 $ op [2:0] $end
$scope module dut $end
$var wire 8 % A [7:0] $end
$var wire 8 & B [7:0] $end
$var wire 3 ' op [2:0] $end
$var reg 8 ( result [7:0] $end
$upscope $end
$upscope $end
$enddefinitions $end
#0
$dumpvars
b10000001 (
b0 '
b1 &
b10000000 %
b0 $
b1 #
b10000000 "
b10000001 !
$end
#10
b1111111 !
b1111111 (
b1 $
b1 '
#20
b11111111 !
b11111111 (
b10 $
b10 '
#30
b10000001 !
b10000001 (
b11 $
b11 '
#40
b1111110 !
b1111110 (
b100 $
b100 '
#50
b101 $
b101 '
#60
b0 !
b0 (
b110 $
b110 '
#70
b111 $
b111 '
